space_os/__init__.py
space_os-0.0.1.dist-info/METADATA
space_os-0.0.1.dist-info/WHEEL
space_os-0.0.1.dist-info/RECORD
